Workbook

Sheet  TODO
A1: TACHE | B1: PAGE | C1: DÉTAIL | D1: TYPE | E1: QUI | F1: ESTIMATION (min) | G1: TEMPS PASSÉ (min) | H1: RESTE À FAIRE (min) | I1: AVANCEMENT | J1: ÉTAT
A2: INSCRIPTION | B2: users.sql | C2: Table users : id, nom, prenom, email, mdp, genre, taille, poids, imc, wallet, is_gold | D2: SQL | E2: Steeven | F2: 20 | G2: 0 | H2: =MAX(0,F2-G2) -> 20 | I2: =IFERROR(MIN(1,G2/F2),0) -> 0 | J2: =IF(G2=0,"À FAIRE",IF(I2>=1,"OK","EN COURS")) -> À FAIRE
A3: INSCRIPTION | B3: register_step1.php | C3: Design HTML/CSS formulaire étape 1 : nom, prénom, email, genre | D3: HTML/CSS | E3: Steeven | F3: 60 | G3: 0 | H3: =MAX(0,F3-G3) -> 60 | I3: =IFERROR(MIN(1,G3/F3),0) -> 0 | J3: =IF(G3=0,"À FAIRE",IF(I3>=1,"OK","EN COURS")) -> À FAIRE
A4: INSCRIPTION | B4: register_step1.php | C4: Validation JS côté client : champs obligatoires, format email | D4: JavaScript | E4: Steeven | F4: 40 | G4: 0 | H4: =MAX(0,F4-G4) -> 40 | I4: =IFERROR(MIN(1,G4/F4),0) -> 0 | J4: =IF(G4=0,"À FAIRE",IF(I4>=1,"OK","EN COURS")) -> À FAIRE
A5: INSCRIPTION | B5: register_step2.php | C5: Design HTML/CSS formulaire étape 2 : taille (cm), poids (kg) | D5: HTML/CSS | E5: Steeven | F5: 50 | G5: 0 | H5: =MAX(0,F5-G5) -> 50 | I5: =IFERROR(MIN(1,G5/F5),0) -> 0 | J5: =IF(G5=0,"À FAIRE",IF(I5>=1,"OK","EN COURS")) -> À FAIRE
A6: INSCRIPTION | B6: register_step2.php | C6: Calcul et affichage IMC en temps réel (AJAX) | D6: JavaScript/AJAX | E6: Steeven | F6: 50 | G6: 0 | H6: =MAX(0,F6-G6) -> 50 | I6: =IFERROR(MIN(1,G6/F6),0) -> 0 | J6: =IF(G6=0,"À FAIRE",IF(I6>=1,"OK","EN COURS")) -> À FAIRE
A7: INSCRIPTION | B7: AuthController.php | C7: Logique inscription 2 étapes : session entre pages, hash mdp, insertion BDD | D7: PHP/CodeIgniter | E7: Steeven | F7: 90 | G7: 0 | H7: =MAX(0,F7-G7) -> 90 | I7: =IFERROR(MIN(1,G7/F7),0) -> 0 | J7: =IF(G7=0,"À FAIRE",IF(I7>=1,"OK","EN COURS")) -> À FAIRE
A8: LOGIN | B8: login.php | C8: Design page login : champs email + mot de passe + bouton | D8: HTML/CSS | E8: Mihaja | F8: 40 | G8: 0 | H8: =MAX(0,F8-G8) -> 40 | I8: =IFERROR(MIN(1,G8/F8),0) -> 0 | J8: =IF(G8=0,"À FAIRE",IF(I8>=1,"OK","EN COURS")) -> À FAIRE
A9: LOGIN | B9: AuthController.php | C9: Logique login : vérif hash mdp, session CI4, logout, filtre auth | D9: PHP/CodeIgniter | E9: Mihaja | F9: 70 | G9: 0 | H9: =MAX(0,F9-G9) -> 70 | I9: =IFERROR(MIN(1,G9/F9),0) -> 0 | J9: =IF(G9=0,"À FAIRE",IF(I9>=1,"OK","EN COURS")) -> À FAIRE
A10: PROFIL | B10: profile.php | C10: Design page profil : affichage + formulaire édition | D10: HTML/CSS | E10: Aina | F10: 60 | G10: 0 | H10: =MAX(0,F10-G10) -> 60 | I10: =IFERROR(MIN(1,G10/F10),0) -> 0 | J10: =IF(G10=0,"À FAIRE",IF(I10>=1,"OK","EN COURS")) -> À FAIRE
A11: PROFIL | B11: ProfileController.php | C11: Mise à jour profil via AJAX + recalcul IMC | D11: PHP/AJAX | E11: Aina | F11: 60 | G11: 0 | H11: =MAX(0,F11-G11) -> 60 | I11: =IFERROR(MIN(1,G11/F11),0) -> 0 | J11: =IF(G11=0,"À FAIRE",IF(I11>=1,"OK","EN COURS")) -> À FAIRE
A12: OBJECTIF | B12: objectif.php | C12: Design page : 3 cartes cliquables (augmenter, réduire, IMC idéal) | D12: HTML/CSS | E12: Mihaja | F12: 55 | G12: 0 | H12: =MAX(0,F12-G12) -> 55 | I12: =IFERROR(MIN(1,G12/F12),0) -> 0 | J12: =IF(G12=0,"À FAIRE",IF(I12>=1,"OK","EN COURS")) -> À FAIRE
A13: OBJECTIF | B13: ObjectifController.php | C13: Sauvegarde objectif en session + base + redirection vers suggestion | D13: PHP/CodeIgniter | E13: Mihaja | F13: 35 | G13: 0 | H13: =MAX(0,F13-G13) -> 35 | I13: =IFERROR(MIN(1,G13/F13),0) -> 0 | J13: =IF(G13=0,"À FAIRE",IF(I13>=1,"OK","EN COURS")) -> À FAIRE
... A53: TESTS & LIVRAISON | B53: gitlab | C53: Revue finale du code, merge branches → main, tag de version livraison | D53: Général | E53: Steeven | F53: 25 | G53: 0 | H53: =MAX(0,F53-G53) -> 25 | I53: =IFERROR(MIN(1,G53/F53),0) -> 0 | J53: =IF(G53=0,"À FAIRE",IF(I53>=1,"OK","EN COURS")) -> À FAIRE

Sheet  RÉSUMÉ
A1: RÉSUMÉ GLOBAL DU PROJET
A2: ESTIMATION TOTALE (min) | B2: TEMPS PASSÉ TOTAL (min) | C2: RESTE TOTAL (min) | D2: AVANCEMENT GLOBAL | E2: NB TÂCHES | F2: NB TÂCHES TERMINÉES
A3: =SUM(' TODO'!F2:F53) -> 2680 | B3: =SUM(' TODO'!G2:G53) -> 0 | C3: =SUM(' TODO'!H2:H53) -> 2680 | D3: =IFERROR(C3/B3,0) -> 0 | E3: =COUNTA(' TODO'!A2:A53) -> 52 | F3: =COUNTIF(' TODO'!J2:J53,"OK") -> 0
A5: SUIVI PAR PERSONNE
A6: PERSONNE | B6: NB TÂCHES | C6: ESTIMATION (min) | D6: TEMPS PASSÉ (min) | E6: RESTE (min) | F6: AVANCEMENT | G6: NB TERMINÉES
A7: Steeven | B7: =COUNTIF(' TODO'!E2:E53,"Steeven") -> 20 | C7: =SUMIF(' TODO'!E2:E53,"Steeven",' TODO'!F2:F53) -> 950 | D7: =SUMIF(' TODO'!E2:E53,"Steeven",' TODO'!G2:G53) -> 0 | E7: =SUMIF(' TODO'!E2:E53,"Steeven",' TODO'!H2:H53) -> 950 | F7: =IFERROR(D7/C7,0) -> 0 | G7: =SUMPRODUCT((' TODO'!E2:E53="Steeven")*(' TODO'!J2:J53="OK")) -> 0
A8: Mihaja | B8: =COUNTIF(' TODO'!E2:E53,"Mihaja") -> 17 | C8: =SUMIF(' TODO'!E2:E53,"Mihaja",' TODO'!F2:F53) -> 845 | D8: =SUMIF(' TODO'!E2:E53,"Mihaja",' TODO'!G2:G53) -> 0 | E8: =SUMIF(' TODO'!E2:E53,"Mihaja",' TODO'!H2:H53) -> 845 | F8: =IFERROR(D8/C8,0) -> 0 | G8: =SUMPRODUCT((' TODO'!E2:E53="Mihaja")*(' TODO'!J2:J53="OK")) -> 0
A9: Aina | B9: =COUNTIF(' TODO'!E2:E53,"Aina") -> 15 | C9: =SUMIF(' TODO'!E2:E53,"Aina",' TODO'!F2:F53) -> 885 | D9: =SUMIF(' TODO'!E2:E53,"Aina",' TODO'!G2:G53) -> 0 | E9: =SUMIF(' TODO'!E2:E53,"Aina",' TODO'!H2:H53) -> 885 | F9: =IFERROR(D9/C9,0) -> 0 | G9: =SUMPRODUCT((' TODO'!E2:E53="Aina")*(' TODO'!J2:J53="OK")) -> 0
A10: TOTAL | B10: =SUM(B7:B9) -> 52 | C10: =SUM(C7:C9) -> 2680 | D10: =SUM(D7:D9) -> 0 | E10: =SUM(E7:E9) -> 2680 | F10: =IFERROR(D10/C10,0) -> 0 | G10: =SUM(G7:G9) -> 0

Sheet TABLEAU CROISÉ
A1: TABLEAU CROISÉ : ESTIMATION (min) PAR MODULE × PERSONNE
A2: MODULE | B2: Steeven | C2: Mihaja | D2: Aina | E2: TOTAL (min)
A3: INSCRIPTION | B3: =SUMPRODUCT((' TODO'!A2:A53="INSCRIPTION")*(' TODO'!E2:E53="Steeven")*(' TODO'!F2:F53)) -> 310 | C3: =SUMPRODUCT((' TODO'!A2:A53="INSCRIPTION")*(' TODO'!E2:E53="Mihaja")*(' TODO'!F2:F53)) -> 0 | D3: =SUMPRODUCT((' TODO'!A2:A53="INSCRIPTION")*(' TODO'!E2:E53="Aina")*(' TODO'!F2:F53)) -> 0 | E3: =SUM(B3:D3) -> 310
A4: LOGIN | B4: =SUMPRODUCT((' TODO'!A2:A53="LOGIN")*(' TODO'!E2:E53="Steeven")*(' TODO'!F2:F53)) -> 0 | C4: =SUMPRODUCT((' TODO'!A2:A53="LOGIN")*(' TODO'!E2:E53="Mihaja")*(' TODO'!F2:F53)) -> 110 | D4: =SUMPRODUCT((' TODO'!A2:A53="LOGIN")*(' TODO'!E2:E53="Aina")*(' TODO'!F2:F53)) -> 0 | E4: =SUM(B4:D4) -> 110
A5: PROFIL | B5: =SUMPRODUCT((' TODO'!A2:A53="PROFIL")*(' TODO'!E2:E53="Steeven")*(' TODO'!F2:F53)) -> 0 | C5: =SUMPRODUCT((' TODO'!A2:A53="PROFIL")*(' TODO'!E2:E53="Mihaja")*(' TODO'!F2:F53)) -> 0 | D5: =SUMPRODUCT((' TODO'!A2:A53="PROFIL")*(' TODO'!E2:E53="Aina")*(' TODO'!F2:F53)) -> 120 | E5: =SUM(B5:D5) -> 120
A6: OBJECTIF | B6: =SUMPRODUCT((' TODO'!A2:A53="OBJECTIF")*(' TODO'!E2:E53="Steeven")*(' TODO'!F2:F53)) -> 0 | C6: =SUMPRODUCT((' TODO'!A2:A53="OBJECTIF")*(' TODO'!E2:E53="Mihaja")*(' TODO'!F2:F53)) -> 90 | D6: =SUMPRODUCT((' TODO'!A2:A53="OBJECTIF")*(' TODO'!E2:E53="Aina")*(' TODO'!F2:F53)) -> 0 | E6: =SUM(B6:D6) -> 90
A7: SUGGESTION | B7: =SUMPRODUCT((' TODO'!A2:A53="SUGGESTION")*(' TODO'!E2:E53="Steeven")*(' TODO'!F2:F53)) -> 55 | C7: =SUMPRODUCT((' TODO'!A2:A53="SUGGESTION")*(' TODO'!E2:E53="Mihaja")*(' TODO'!F2:F53)) -> 0 | D7: =SUMPRODUCT((' TODO'!A2:A53="SUGGESTION")*(' TODO'!E2:E53="Aina")*(' TODO'!F2:F53)) -> 240 | E7: =SUM(B7:D7) -> 295
A8: EXPORT PDF | B8: =SUMPRODUCT((' TODO'!A2:A53="EXPORT PDF")*(' TODO'!E2:E53="Steeven")*(' TODO'!F2:F53)) -> 0 | C8: =SUMPRODUCT((' TODO'!A2:A53="EXPORT PDF")*(' TODO'!E2:E53="Mihaja")*(' TODO'!F2:F53)) -> 135 | D8: =SUMPRODUCT((' TODO'!A2:A53="EXPORT PDF")*(' TODO'!E2:E53="Aina")*(' TODO'!F2:F53)) -> 0 | E8: =SUM(B8:D8) -> 135
A9: PORTE MONNAIE | B9: =SUMPRODUCT((' TODO'!A2:A53="PORTE MONNAIE")*(' TODO'!E2:E53="Steeven")*(' TODO'!F2:F53)) -> 125 | C9: =SUMPRODUCT((' TODO'!A2:A53="PORTE MONNAIE")*(' TODO'!E2:E53="Mihaja")*(' TODO'!F2:F53)) -> 0 | D9: =SUMPRODUCT((' TODO'!A2:A53="PORTE MONNAIE")*(' TODO'!E2:E53="Aina")*(' TODO'!F2:F53)) -> 0 | E9: =SUM(B9:D9) -> 125
A10: OPTION GOLD | B10: =SUMPRODUCT((' TODO'!A2:A53="OPTION GOLD")*(' TODO'!E2:E53="Steeven")*(' TODO'!F2:F53)) -> 30 | C10: =SUMPRODUCT((' TODO'!A2:A53="OPTION GOLD")*(' TODO'!E2:E53="Mihaja")*(' TODO'!F2:F53)) -> 105 | D10: =SUMPRODUCT((' TODO'!A2:A53="OPTION GOLD")*(' TODO'!E2:E53="Aina")*(' TODO'!F2:F53)) -> 0 | E10: =SUM(B10:D10) -> 135
A11: NAVIGATION | B11: =SUMPRODUCT((' TODO'!A2:A53="NAVIGATION")*(' TODO'!E2:E53="Steeven")*(' TODO'!F2:F53)) -> 0 | C11: =SUMPRODUCT((' TODO'!A2:A53="NAVIGATION")*(' TODO'!E2:E53="Mihaja")*(' TODO'!F2:F53)) -> 0 | D11: =SUMPRODUCT((' TODO'!A2:A53="NAVIGATION")*(' TODO'!E2:E53="Aina")*(' TODO'!F2:F53)) -> 105 | E11: =SUM(B11:D11) -> 105
A12: BO LOGIN | B12: =SUMPRODUCT((' TODO'!A2:A53="BO LOGIN")*(' TODO'!E2:E53="Steeven")*(' TODO'!F2:F53)) -> 0 | C12: =SUMPRODUCT((' TODO'!A2:A53="BO LOGIN")*(' TODO'!E2:E53="Mihaja")*(' TODO'!F2:F53)) -> 80 | D12: =SUMPRODUCT((' TODO'!A2:A53="BO LOGIN")*(' TODO'!E2:E53="Aina")*(' TODO'!F2:F53)) -> 0 | E12: =SUM(B12:D12) -> 80
A13: BO DASHBOARD | B13: =SUMPRODUCT((' TODO'!A2:A53="BO DASHBOARD")*(' TODO'!E2:E53="Steeven")*(' TODO'!F2:F53)) -> 75 | C13: =SUMPRODUCT((' TODO'!A2:A53="BO DASHBOARD")*(' TODO'!E2:E53="Mihaja")*(' TODO'!F2:F53)) -> 60 | D13: =SUMPRODUCT((' TODO'!A2:A53="BO DASHBOARD")*(' TODO'!E2:E53="Aina")*(' TODO'!F2:F53)) -> 135 | E13: =SUM(B13:D13) -> 270
A14: BO RÉGIMES | B14: =SUMPRODUCT((' TODO'!A2:A53="BO RÉGIMES")*(' TODO'!E2:E53="Steeven")*(' TODO'!F2:F53)) -> 105 | C14: =SUMPRODUCT((' TODO'!A2:A53="BO RÉGIMES")*(' TODO'!E2:E53="Mihaja")*(' TODO'!F2:F53)) -> 65 | D14: =SUMPRODUCT((' TODO'!A2:A53="BO RÉGIMES")*(' TODO'!E2:E53="Aina")*(' TODO'!F2:F53)) -> 55 | E14: =SUM(B14:D14) -> 225
A15: BO ACTIVITÉS | B15: =SUMPRODUCT((' TODO'!A2:A53="BO ACTIVITÉS")*(' TODO'!E2:E53="Steeven")*(' TODO'!F2:F53)) -> 0 | C15: =SUMPRODUCT((' TODO'!A2:A53="BO ACTIVITÉS")*(' TODO'!E2:E53="Mihaja")*(' TODO'!F2:F53)) -> 75 | D15: =SUMPRODUCT((' TODO'!A2:A53="BO ACTIVITÉS")*(' TODO'!E2:E53="Aina")*(' TODO'!F2:F53)) -> 90 | E15: =SUM(B15:D15) -> 165
A16: BO CODES | B16: =SUMPRODUCT((' TODO'!A2:A53="BO CODES")*(' TODO'!E2:E53="Steeven")*(' TODO'!F2:F53)) -> 150 | C16: =SUMPRODUCT((' TODO'!A2:A53="BO CODES")*(' TODO'!E2:E53="Mihaja")*(' TODO'!F2:F53)) -> 0 | D16: =SUMPRODUCT((' TODO'!A2:A53="BO CODES")*(' TODO'!E2:E53="Aina")*(' TODO'!F2:F53)) -> 0 | E16: =SUM(B16:D16) -> 150
A17: BO PARAMÈTRES | B17: =SUMPRODUCT((' TODO'!A2:A53="BO PARAMÈTRES")*(' TODO'!E2:E53="Steeven")*(' TODO'!F2:F53)) -> 0 | C17: =SUMPRODUCT((' TODO'!A2:A53="BO PARAMÈTRES")*(' TODO'!E2:E53="Mihaja")*(' TODO'!F2:F53)) -> 10 | D17: =SUMPRODUCT((' TODO'!A2:A53="BO PARAMÈTRES")*(' TODO'!E2:E53="Aina")*(' TODO'!F2:F53)) -> 90 | E17: =SUM(B17:D17) -> 100
A18: BASE DE DONNÉES | B18: =SUMPRODUCT((' TODO'!A2:A53="BASE DE DONNÉES")*(' TODO'!E2:E53="Steeven")*(' TODO'!F2:F53)) -> 45 | C18: =SUMPRODUCT((' TODO'!A2:A53="BASE DE DONNÉES")*(' TODO'!E2:E53="Mihaja")*(' TODO'!F2:F53)) -> 55 | D18: =SUMPRODUCT((' TODO'!A2:A53="BASE DE DONNÉES")*(' TODO'!E2:E53="Aina")*(' TODO'!F2:F53)) -> 0 | E18: =SUM(B18:D18) -> 100
A19: TESTS & LIVRAISON | B19: =SUMPRODUCT((' TODO'!A2:A53="TESTS & LIVRAISON")*(' TODO'!E2:E53="Steeven")*(' TODO'!F2:F53)) -> 55 | C19: =SUMPRODUCT((' TODO'!A2:A53="TESTS & LIVRAISON")*(' TODO'!E2:E53="Mihaja")*(' TODO'!F2:F53)) -> 60 | D19: =SUMPRODUCT((' TODO'!A2:A53="TESTS & LIVRAISON")*(' TODO'!E2:E53="Aina")*(' TODO'!F2:F53)) -> 50 | E19: =SUM(B19:D19) -> 165
A20: TOTAL (min) | B20: =SUM(B3:B19) -> 950 | C20: =SUM(C3:C19) -> 845 | D20: =SUM(D3:D19) -> 885 | E20: =SUM(E3:E19) -> 2680
A22: TABLEAU CROISÉ : NB TÂCHES PAR PERSONNE × ÉTAT
A23: PERSONNE | B23: À FAIRE | C23: EN COURS | D23: OK | E23: TOTAL
A24: Steeven | B24: =SUMPRODUCT((' TODO'!E2:E53="Steeven")*(' TODO'!J2:J53="À FAIRE")) -> 20 | C24: =SUMPRODUCT((' TODO'!E2:E53="Steeven")*(' TODO'!J2:J53="EN COURS")) -> 0 | D24: =SUMPRODUCT((' TODO'!E2:E53="Steeven")*(' TODO'!J2:J53="OK")) -> 0 | E24: =SUM(B24:D24) -> 20
A25: Mihaja | B25: =SUMPRODUCT((' TODO'!E2:E53="Mihaja")*(' TODO'!J2:J53="À FAIRE")) -> 17 | C25: =SUMPRODUCT((' TODO'!E2:E53="Mihaja")*(' TODO'!J2:J53="EN COURS")) -> 0 | D25: =SUMPRODUCT((' TODO'!E2:E53="Mihaja")*(' TODO'!J2:J53="OK")) -> 0 | E25: =SUM(B25:D25) -> 17
A26: Aina | B26: =SUMPRODUCT((' TODO'!E2:E53="Aina")*(' TODO'!J2:J53="À FAIRE")) -> 15 | C26: =SUMPRODUCT((' TODO'!E2:E53="Aina")*(' TODO'!J2:J53="EN COURS")) -> 0 | D26: =SUMPRODUCT((' TODO'!E2:E53="Aina")*(' TODO'!J2:J53="OK")) -> 0 | E26: =SUM(B26:D26) -> 15
A27: TOTAL | B27: =SUM(B24:B26) -> 52 | C27: =SUM(C24:C26) -> 0 | D27: =SUM(D24:D26) -> 0 | E27: =SUM(E24:E26) -> 52
